kgraphservice/__init__.py
kgraphservice/kg_comparator.py
kgraphservice/kgraph_service.py
kgraphservice/kgraph_service_inf.py
kgraphservice/kgraph_service_rest.py
kgraphservice/kgslot_criterion.py
kgraphservice/binary/__init__.py
kgraphservice/binary/binary_service.py
kgraphservice/binary/s3_impl.py
kgraphservice/client/__init__.py
kgraphservice/client/kgraphservice_client.py
kgraphservice/collection/__init__.py
kgraphservice/collection/kgraph_collection.py
kgraphservice/config/__init__.py
kgraphservice/config/config_utils.py
kgraphservice/frame/__init__.py
kgraphservice/frame/frame_query_executor.py
kgraphservice/frame/frame_query_generator.py
kgraphservice/frame/frame_query_processor.py
kgraphservice/impl/__init__.py
kgraphservice/inf/__init__.py
kgraphservice/inf/kgraph_service_inf.py
kgraphservice/info/__init__.py
kgraphservice/info/frame_info.py
kgraphservice/info/interaction_info.py
kgraphservice/info/kgraph_info.py
kgraphservice/mgr/__init__.py
kgraphservice/mgr/kgraph_service_manager.py
kgraphservice/ontology/__init__.py
kgraphservice/ontology/ontology_query_manager.py
kgraphservice/ops/__init__.py
kgraphservice/ops/event_ops.py
kgraphservice/part/__init__.py
kgraphservice/part/kgchatevent_message_bot_part.py
kgraphservice/part/kgchatevent_message_part.py
kgraphservice/part/kgchatevent_message_user_part.py
kgraphservice/part/kgdocument_part.py
kgraphservice/part/kgentity_part.py
kgraphservice/part/kgframe_part.py
kgraphservice/part/kgnode_part.py
kgraphservice/query/__init__.py
kgraphservice/query/construct_query.py
kgraphservice/query/event_query_generator.py
kgraphservice/query/frame_query_generator.py
kgraphservice/query/kg_comparator.py
kgraphservice/query/kgslot_criterion.py
kgraphservice/query/relation_query_generator.py
kgraphservice/query/traverse_query_generator.py
kgraphservice/rest/__init__.py
kgraphservice/rest/app.py
kgraphservice/rest/kgraphservice_rest_impl.py
kgraphservice/rest/impl/__init__.py
kgraphservice/rest/impl/kgraphservice_builder.py
kgraphservice-0.0.8.dist-info/LICENSE
kgraphservice-0.0.8.dist-info/METADATA
kgraphservice-0.0.8.dist-info/WHEEL
kgraphservice-0.0.8.dist-info/top_level.txt
kgraphservice-0.0.8.dist-info/RECORD
