Metadata-Version: 2.1
Name: kgraphservice
Version: 0.0.8
Summary: KGraph Service
Home-page: https://github.com/vital-ai/kgraphservice
Author: Marc Hadfield
Author-email: marc@vital.ai
License: Apache License 2.0
Classifier: Programming Language :: Python :: 3.12
Classifier: License :: OSI Approved :: Apache Software License
Classifier: Operating System :: OS Independent
Requires-Python: >=3.12
License-File: LICENSE
Requires-Dist: vital-ai-vitalsigns>=0.1.32
Requires-Dist: vital-ai-domain>=0.1.7
Requires-Dist: six==1.16.0
Requires-Dist: pyyaml==6.0.2
Requires-Dist: vital-ai-haley-kg>=0.1.24
Requires-Dist: rdflib>=7.0.0
Requires-Dist: SPARQLWrapper==2.0.0
Requires-Dist: networkx>=3.3
Requires-Dist: uvicorn[standard]>=0.27.0.post1
Requires-Dist: fastapi>=0.109.2
Requires-Dist: requests==2.32.3
Requires-Dist: boto3>=1.35.36
Requires-Dist: aioboto3>=13.2.0
Requires-Dist: python-multipart>=0.0.12
